{
  "sessionCapacity": 12,
  "sessionCount": 2,
  "speakers": [
    {
      "speakerName": "蘇柏瑄 Brian Su",
      "avatar": "https://sitcon.camp/2026/avatars/speakers/brian-su.jpg",
      "description": "台大資訊系畢業，現於香港擔任軟體工程師。小學四年級起接觸到程式，除了寫過各種 hobby project 以外，還參加過世界機器人奧林匹克、國際科展、國際資奧、與國際大學生程式設計競賽等大大小小的比賽——其中曾以台灣歷史最佳名次取得國際資奧金牌。也參與過多次 SITCON 活動並曾任年會議程組副組長。大學時誤打誤撞的進入了間金融公司實習，現在是個全職的軟體工程師，主要投入在開發簡潔與可維護的程式。"
    },
    {
      "speakerName": "趙式隆",
      "avatar": "https://sitcon.camp/2026/avatars/speakers/shih-lung-chao.webp",
      "description": "趙式隆先生為現任北市府資訊局局長，作為資料科學家與行動主義者，他致力於推動開放原始碼，打造臺北成為數位世界中的自由、平等與博愛之城。作為連續創業者，他前後創辦了教育科技平台 Zuvio\n與保險科技龍頭 BravoAI。作為學者，他是臺大創創的共同創辦人，現仍兼任該學程副教授，並曾任教於臺大電機系與陽明交大經管所。"
    }
  ]
}
